{
  "Dr. Tima Renáta": "dr. Tima Renáta",
  "Dr. Tima Renáta Judit": "dr. Tima Renáta",
  "Kelemen Ferenc": "Kelemen Ferenc Mihály",
  "Dr. Miléné Papp Ágota": "dr. Miléné Papp Ágota",
  "Dr. Herber Attila": "dr. Herber Attila",
  "Rujpné Pártos Boglárka Andrea": "Rujpné Pártos Boglárka",
  "Dr. Lakatos István": "dr. Lakatos István",
  "Baranyai Balázs Lajos": "Baranyai Balázs",
  "Horváthné Bujtás Anna Mária": "Horváthné Bujtás Anna",
  "Sándor István Zoltán": "Sándor István",
  "Dr. Bárdosné Páhy Judit Katalin": "Dr. Bárdosné Páhy Judit",
  "Solymoss Miklós Marcell": "Solymoss Miklós",
  "Húnfalviné Bognár Anikó": "Hunfalviné Bognár Anikó",
  "Molnár Boglárka Éva": "Molnár Boglárka",
  "Mongyi Norbert József": "Mongyi Norbert",
  "Barkó Ferenc József": "Barkó Ferenc",
  "Némethné Tudja Éva Ilona": "Némethné Tudja Éva",
  "Kiss Tamás György": "Kiss Tamás",
  "Balogh Andrea Katalin": "Balogh Andrea",
  "Gyurta Noel Gábor": "Gyurta Noel",
  "Szabóné Lukács Andrea Éva": "Szabóné Lukács Andrea",
  "Tomozi Anna Zsófia": "Tomozi Zsófia",
  "Varga (VéBé) Balázs": "Varga Balázs",
  "Hegedűs Ilona Beáta": "Hegedűs Ilona",
  "Hegedûs Ilona Beáta": "Hegedűs Ilona"
}
